flake8_datetime_utcnow/__init__.py
flake8_datetime_utcnow/__version__.py
flake8_datetime_utcnow/linter.py
flake8_datetime_utcnow/visitor.py
flake8_datetime_utcnow_plugin-0.1.2.dist-info/entry_points.txt
flake8_datetime_utcnow_plugin-0.1.2.dist-info/LICENSE
flake8_datetime_utcnow_plugin-0.1.2.dist-info/WHEEL
flake8_datetime_utcnow_plugin-0.1.2.dist-info/METADATA
flake8_datetime_utcnow_plugin-0.1.2.dist-info/RECORD
