Metadata-Version: 2.1
Name: flake8-datetime-utcnow-plugin
Version: 0.1.2
Summary: Plugin to check that utcnow() is not used in favour of now(UTC)
Home-page: https://github.com/expobrain/flake8-datetime-utcnow-plugin
License: MIT
Author: Daniele Esposti
Author-email: daniele.esposti@gmail.com
Requires-Python: >=3.7,<4
Classifier: Environment :: Console
Classifier: Framework :: Flake8
Classifier: Intended Audience :: Developers
Classifier: License :: OSI Approved :: MIT License
Classifier: Programming Language :: Python
Classifier: Programming Language :: Python :: 3
Classifier: Programming Language :: Python :: 3.10
Classifier: Programming Language :: Python :: 3.7
Classifier: Programming Language :: Python :: 3.8
Classifier: Programming Language :: Python :: 3.9
Classifier: Topic :: Software Development :: Libraries :: Python Modules
Classifier: Topic :: Software Development :: Quality Assurance
Requires-Dist: flake8 (>=3.0.0)
Project-URL: Repository, https://github.com/expobrain/flake8-datetime-utcnow-plugin
